business_api_client/__init__.py
business_api_client/api_client.py
business_api_client/configuration.py
business_api_client/response.py
business_api_client/rest.py
business_api_client/api/__init__.py
business_api_client/api/account_api.py
business_api_client/api/account_management_api.py
business_api_client/api/ad_aco_api.py
business_api_client/api/ad_api.py
business_api_client/api/adgroup_api.py
business_api_client/api/app_management_api.py
business_api_client/api/audience_api.py
business_api_client/api/authentication_api.py
business_api_client/api/automated_rules_api.py
business_api_client/api/bc_api.py
business_api_client/api/bc_payment_api.py
business_api_client/api/campaign_creation_api.py
business_api_client/api/catalog_api.py
business_api_client/api/comments_api.py
business_api_client/api/creative_asset_api.py
business_api_client/api/creative_management_api.py
business_api_client/api/event_callback_api.py
business_api_client/api/file_api.py
business_api_client/api/identity_api.py
business_api_client/api/measurement_api.py
business_api_client/api/recommend_tool_api.py
business_api_client/api/reporting_api.py
business_api_client/api/store_api.py
business_api_client/api/tool_api.py
business_api_client/api/video_api.py
business_api_client/models/__init__.py
business_api_client/models/ad_aco_body.py
business_api_client/models/ad_aco_body_avatar_icon.py
business_api_client/models/ad_aco_body_avatar_icon_list.py
business_api_client/models/ad_aco_body_call_to_action_list.py
business_api_client/models/ad_aco_body_card_list.py
business_api_client/models/ad_aco_body_common_material.py
business_api_client/models/ad_aco_body_common_material_tracking_info.py
business_api_client/models/ad_aco_body_deeplink_list.py
business_api_client/models/ad_aco_body_display_name_list.py
business_api_client/models/ad_aco_body_landing_page_urls.py
business_api_client/models/ad_aco_body_media_info.py
business_api_client/models/ad_aco_body_media_info_image_info.py
tiktok_business_api_sdk_official-1.1.2.dist-info/METADATA
tiktok_business_api_sdk_official-1.1.2.dist-info/WHEEL
tiktok_business_api_sdk_official-1.1.2.dist-info/top_level.txt
tiktok_business_api_sdk_official-1.1.2.dist-info/RECORD
