Metadata-Version: 2.4
Name: tiktok-business-api-sdk-official
Version: 1.1.2
Summary: TikTok Business API SDK
Home-page: https://github.com/tiktok/tiktok-business-api-sdk
Author: TikTok Pte. Ltd.
Author-email: jason.chen@tiktok.com
Keywords: Swagger,TikTok Business API SDK
Classifier: Programming Language :: Python :: 3
Classifier: License :: OSI Approved :: MIT License
Classifier: Operating System :: OS Independent
Requires-Python: >=3.4
Requires-Dist: urllib3>=1.15
Requires-Dist: six>=1.10
Requires-Dist: certifi
Requires-Dist: python-dateutil
Dynamic: author
Dynamic: author-email
Dynamic: classifier
Dynamic: description
Dynamic: description-content-type
Dynamic: home-page
Dynamic: keywords
Dynamic: requires-dist
Dynamic: requires-python
Dynamic: summary
